[{"id":6062,"coords":{"lat":24.3733,"lng":88.6049},"content":"<p>Name: Shakil Khan<br>Occupation: Student<br>Interest: Programming<\/p><br><a href='viewProfile.php?id=6062' class=''>View Profile<\/a> &nbsp; &nbsp; <a href='inbox.php?id=6062'>chat<\/a>"},{"id":6,"coords":{"lat":21.5641,"lng":92.0282},"content":"<p>Name: Riad Opu<br>Occupation: Student<br>Interest: Game<\/p><br><a href='viewProfile.php?id=6' class=''>View Profile<\/a> &nbsp; &nbsp; <a href='inbox.php?id=6'>chat<\/a>"},{"id":9570,"coords":{"lat":22.6738,"lng":89.3967},"content":"<p>Name: Nafisha Rahman<br>Occupation: Doctor<br>Interest: Music<\/p><br><a href='viewProfile.php?id=9570' class=''>View Profile<\/a> &nbsp; &nbsp; <a href='inbox.php?id=9570'>chat<\/a>"},{"id":5766,"coords":{"lat":25.6279,"lng":88.6332},"content":"<p>Name: Naeemul Haque<br>Occupation: Singer<br>Interest: Music<\/p><br><a href='viewProfile.php?id=5766' class=''>View Profile<\/a> &nbsp; &nbsp; <a href='inbox.php?id=5766'>chat<\/a>"},{"id":2604,"coords":{"lat":23.8105,"lng":90.3372},"content":"<p>Name: Rafid Ahsan<br>Occupation: Web Developer<br>Interest: Programming<\/p><br><a href='viewProfile.php?id=2604' class=''>View Profile<\/a> &nbsp; &nbsp; <a href='inbox.php?id=2604'>chat<\/a>"},{"id":541885065,"coords":{"lat":23.7147,"lng":90.5636},"content":"<p>Name: Saba Ahmed<br>Occupation: joker<br>Interest: Cricket<\/p><br><a href='viewProfile.php?id=541885065' class=''>View Profile<\/a> &nbsp; &nbsp; <a href='inbox.php?id=541885065'>chat<\/a>"}]